markdown_spider/__init__.py
markdown_spider/cli.py
markdown_spider/converter.py
markdown_spider-0.1.1.dist-info/LICENSE
markdown_spider-0.1.1.dist-info/METADATA
markdown_spider-0.1.1.dist-info/WHEEL
markdown_spider-0.1.1.dist-info/entry_points.txt
markdown_spider-0.1.1.dist-info/RECORD
