Metadata-Version: 2.3
Name: markdown-spider
Version: 0.1.1
Summary: A configurable web spider that converts online documentation into well-structured Markdown files while preserving formatting and structure
License: Apache-2.0
Keywords: markdown,spider,web-scraping,documentation,converter,html-to-markdown,archiving,content-extraction,web-crawler,documentation-tool
Author: Tyler House
Author-email: 26489166+tahouse@users.noreply.github.com
Requires-Python: >=3.11
Classifier: Development Status :: 4 - Beta
Classifier: Environment :: Console
Classifier: Intended Audience :: Developers
Classifier: License :: OSI Approved :: Apache Software License
Classifier: Operating System :: OS Independent
Classifier: Programming Language :: Python :: 3
Classifier: Programming Language :: Python :: 3.11
Classifier: Programming Language :: Python :: 3.12
Classifier: Programming Language :: Python :: 3.13
Classifier: Topic :: Internet :: WWW/HTTP
Classifier: Topic :: Software Development :: Documentation
Classifier: Topic :: Text Processing :: Markup :: Markdown
Classifier: Topic :: Utilities
Requires-Dist: beautifulsoup4 (>=4.12.0)
Requires-Dist: click (>=8.1.7)
Requires-Dist: markdownify (>=0.11.6)
Requires-Dist: pyyaml (>=6.0.1)
Requires-Dist: requests (>=2.31.0)
Project-URL: Documentation, https://github.com/tahouse/markdown-spider/blob/main/README.md
Project-URL: Homepage, https://github.com/tahouse/markdown-spider
Project-URL: Repository, https://github.com/tahouse/markdown-spider
